LICENSE
MANIFEST.in
README.txt
setup.py
CleverSheep/__init__.py
CleverSheep/version.py
CleverSheep.egg-info/PKG-INFO
CleverSheep.egg-info/SOURCES.txt
CleverSheep.egg-info/dependency_links.txt
CleverSheep.egg-info/requires.txt
CleverSheep.egg-info/top_level.txt
CleverSheep/App/Config.py
CleverSheep/App/__init__.py
CleverSheep/Extras/ColourTB.py
CleverSheep/Extras/__init__.py
CleverSheep/Extras/ultraTB.py
CleverSheep/Log/FileTracker.py
CleverSheep/Log/LogSupport.py
CleverSheep/Log/__init__.py
CleverSheep/Prog/Args.py
CleverSheep/Prog/Aspects.py
CleverSheep/Prog/CStruct.py
CleverSheep/Prog/Curry.py
CleverSheep/Prog/Dict.py
CleverSheep/Prog/Enum.py
CleverSheep/Prog/Files.py
CleverSheep/Prog/Inspect.py
CleverSheep/Prog/Intern.py
CleverSheep/Prog/Iter.py
CleverSheep/Prog/LruCache.py
CleverSheep/Prog/Process.py
CleverSheep/Prog/SortedQ.py
CleverSheep/Prog/__init__.py
CleverSheep/Prog/utils.py
CleverSheep/Sys/Platform.py
CleverSheep/Sys/__init__.py
CleverSheep/TTY_Utils/Colours.py
CleverSheep/TTY_Utils/Indent.py
CleverSheep/TTY_Utils/RichTerm.py
CleverSheep/TTY_Utils/StatusLine.py
CleverSheep/TTY_Utils/__init__.py
CleverSheep/Test/CovParse.py
CleverSheep/Test/DataMaker.py
CleverSheep/Test/ImpUtils.py
CleverSheep/Test/LogTracker.py
CleverSheep/Test/Net.py
CleverSheep/Test/PollManager.py
CleverSheep/Test/ProcMan.py
CleverSheep/Test/SimPoll.py
CleverSheep/Test/Struct.py
CleverSheep/Test/StructDoc.py
CleverSheep/Test/Table.py
CleverSheep/Test/TermEmu.py
CleverSheep/Test/TestEventStore.py
CleverSheep/Test/__init__.py
CleverSheep/Test/cs_asyncio.py
CleverSheep/Test/cs_asyncio_tornado.py
CleverSheep/Test/cs_asyncio_twisted.py
CleverSheep/Test/Mock/Comms.py
CleverSheep/Test/Mock/Component.py
CleverSheep/Test/Mock/__init__.py
CleverSheep/Test/Tester/Assertions.py
CleverSheep/Test/Tester/CmdLine.py
CleverSheep/Test/Tester/Collection.py
CleverSheep/Test/Tester/Context.py
CleverSheep/Test/Tester/Controller.py
CleverSheep/Test/Tester/Coordinator.py
CleverSheep/Test/Tester/Core.py
CleverSheep/Test/Tester/Errors.py
CleverSheep/Test/Tester/Execution.py
CleverSheep/Test/Tester/FloatAssertions.py
CleverSheep/Test/Tester/Journal.py
