Metadata-Version: 1.2
Name: CleverSheep
Version: 0.7.5
Summary: A collection of packages for high level asynchronous testing.
Home-page: https://lcaraccio.gitlab.io/clever-sheep/api/index.html
Author: Paul Ollis, Laurence Caraccio
Author-email: cleversheepframework@gmail.com
License: MIT License
Platform: UNKNOWN
Classifier: License :: OSI Approved :: MIT License
Classifier: Operating System :: POSIX :: Linux
Classifier: Programming Language :: Python :: 2.7
Classifier: Programming Language :: Python :: 3.6
Classifier: Programming Language :: Python :: 3.7
Classifier: Programming Language :: Python :: 3.8
Classifier: Programming Language :: Python :: 3.9
Classifier: Natural Language :: English
Requires-Python: >=2.7, !=3.0.*, !=3.1.*, !=3.2.*, !=3.3.*, !=3.4.*, !=3.5.*, <4
